sheap/Assistants/Parameters.py
sheap/Assistants/__init__.py
sheap/Assistants/parser_mapper.py
sheap/ComplexBuilder/ComplexBuilder.py
sheap/ComplexBuilder/Utils.py
sheap/ComplexBuilder/__init__.py
sheap/ComplexFitting/ComplexFitting.py
sheap/ComplexFitting/__init__.py
sheap/ComplexParams/ComplexParams.py
sheap/ComplexParams/Utils/After_fit_profile_helpers.py
sheap/ComplexParams/Utils/Combine_profiles.py
sheap/ComplexParams/Utils/Physical_functions.py
sheap/ComplexParams/Utils/Sample_handlers.py
sheap/ComplexParams/Utils/__init__.py
sheap/ComplexParams/Utils/fwhm_conv.py
sheap/ComplexParams/__init__.py
sheap/ComplexSampler/ComplexSampler.py
sheap/ComplexSampler/Samplers/McMcSampler.py
sheap/ComplexSampler/Samplers/MonteCarloSampler.py
sheap/ComplexSampler/Samplers/PseudoMonteCarloSampler.py
sheap/ComplexSampler/Samplers/Utils/__init__.py
sheap/ComplexSampler/Samplers/Utils/montecarlo_utils.py
sheap/ComplexSampler/Samplers/Utils/numpyro_utils.py
sheap/ComplexSampler/Samplers/__init__.py
sheap/ComplexSampler/__init__.py
sheap/Core/CoreDataStructures.py
sheap/Core/CoreTypeAliases.py
sheap/Core/__init__.py
sheap/Minimizer/Minimizer.py
sheap/Minimizer/__init__.py
sheap/Minimizer/loss_builder.py
sheap/Plotting/SheapPlot.py
sheap/Plotting/__init__.py
sheap/Plotting/ploting.py
sheap/Plotting/plots_.py
sheap/Profiles/Combine.py
sheap/Profiles/ProfileConstraintMaker.py
sheap/Profiles/Profiles.py
sheap/Profiles/Utils.py
sheap/Profiles/__init__.py
sheap/Profiles/balmercontinuum.py
sheap/Profiles/depreted/Combine.py
sheap/Profiles/depreted/Profiles_s.py
sheap/Profiles/profiles_continuum.py
sheap/Profiles/profiles_lines.py
sheap/Profiles/profiles_lines_loglambda.py
sheap/Profiles/profiles_templates.py
sheap/Sheapectral/Sheapectral.py
sheap/Sheapectral/Utils/BasicCorrections.py
sheap/Sheapectral/Utils/SpectralSetup.py
sheap/Sheapectral/Utils/__init__.py
sheap/Sheapectral/__init__.py
sheap/SuportData/BolometricCorrections/BolometricCorrections.yaml
sheap-0.0.7.dist-info/METADATA
sheap-0.0.7.dist-info/WHEEL
sheap-0.0.7.dist-info/entry_points.txt
sheap-0.0.7.dist-info/licenses/LICENSE
sheap-0.0.7.dist-info/RECORD
